terminalStuffRover/__init__.py
terminalStuffRover/asciiArt.py
terminalStuffRover/terminalStuff.py
terminalstuffrover-2.2.3.dist-info/licenses/LICENSE
terminalstuffrover-2.2.3.dist-info/METADATA
terminalstuffrover-2.2.3.dist-info/WHEEL
terminalstuffrover-2.2.3.dist-info/top_level.txt
terminalstuffrover-2.2.3.dist-info/RECORD
